igbo_text/__init__.py
igbo_text/module.py
igbo_text/test.py
igbo_text-0.1.3.dist-info/LICENSE
igbo_text-0.1.3.dist-info/METADATA
igbo_text-0.1.3.dist-info/WHEEL
igbo_text-0.1.3.dist-info/top_level.txt
igbo_text-0.1.3.dist-info/RECORD
