Metadata-Version: 2.1
Name: igbo-text
Version: 0.1.3
Summary: A python package for tokenizing and normalizing texts mainly written in the Igbo Language
Home-page: https://github.com/goodyduru/igbo-text
Author: Goodness Duru
Author-email: goodyduru@gmail.com
License: UNKNOWN
Platform: UNKNOWN
Classifier: Programming Language :: Python :: 3
Classifier: License :: OSI Approved :: MIT License
Classifier: Operating System :: OS Independent
